dynamodb_lens/__init__.py
dynamodb_lens/analyzer.py
dynamodb_lens/cli.py
dynamodb_lens/utils.py
dynamodb_lens-23.10.dev10.dist-info/LICENSE
dynamodb_lens-23.10.dev10.dist-info/METADATA
dynamodb_lens-23.10.dev10.dist-info/WHEEL
dynamodb_lens-23.10.dev10.dist-info/top_level.txt
dynamodb_lens-23.10.dev10.dist-info/RECORD
