Metadata-Version: 2.1
Name: dynamodb-lens
Version: 23.10.dev10
Summary: DynamoDB Lens - Analyze your DynamoDB environment
Home-page: https://github.com/doitintl/dynamodb-lens.git
Author: Adam North
Author-email: anorth848@gmail.com
License: MIT
Keywords: dynamodb dynamodb-lens
Classifier: Development Status :: 3 - Alpha
Classifier: Intended Audience :: Information Technology
Classifier: License :: OSI Approved :: MIT License
Classifier: Natural Language :: English
Classifier: Operating System :: OS Independent
Classifier: Programming Language :: Python
Classifier: Topic :: Database
Requires-Python: >=3.7
License-File: LICENSE
Requires-Dist: boto3 >=1.28.67
